sphinx_icore_open/__init__.py
sphinx_icore_open/translator.py
sphinx_icore_open/theme/sphinx_icore_open/layout.html
sphinx_icore_open/theme/sphinx_icore_open/search.html
sphinx_icore_open/theme/sphinx_icore_open/theme.conf
sphinx_icore_open/theme/sphinx_icore_open/static/css/theme.css
sphinx_icore_open/theme/sphinx_icore_open/static/fonts/IBMPlexSans/IBMPlexSans-Bold.ttf
sphinx_icore_open/theme/sphinx_icore_open/static/fonts/IBMPlexSans/IBMPlexSans-BoldItalic.ttf
sphinx_icore_open/theme/sphinx_icore_open/static/fonts/IBMPlexSans/IBMPlexSans-ExtraLight.ttf
sphinx_icore_open/theme/sphinx_icore_open/static/fonts/IBMPlexSans/IBMPlexSans-ExtraLightItalic.ttf
sphinx_icore_open/theme/sphinx_icore_open/static/fonts/IBMPlexSans/IBMPlexSans-Italic.ttf
sphinx_icore_open/theme/sphinx_icore_open/static/fonts/IBMPlexSans/IBMPlexSans-Light.ttf
sphinx_icore_open/theme/sphinx_icore_open/static/fonts/IBMPlexSans/IBMPlexSans-LightItalic.ttf
sphinx_icore_open/theme/sphinx_icore_open/static/fonts/IBMPlexSans/IBMPlexSans-Medium.ttf
sphinx_icore_open/theme/sphinx_icore_open/static/fonts/IBMPlexSans/IBMPlexSans-MediumItalic.ttf
sphinx_icore_open/theme/sphinx_icore_open/static/fonts/IBMPlexSans/IBMPlexSans-Regular.ttf
sphinx_icore_open/theme/sphinx_icore_open/static/fonts/IBMPlexSans/IBMPlexSans-SemiBold.ttf
sphinx_icore_open/theme/sphinx_icore_open/static/fonts/IBMPlexSans/IBMPlexSans-SemiBoldItalic.ttf
sphinx_icore_open/theme/sphinx_icore_open/static/fonts/IBMPlexSans/IBMPlexSans-Thin.ttf
sphinx_icore_open/theme/sphinx_icore_open/static/fonts/IBMPlexSans/IBMPlexSans-ThinItalic.ttf
sphinx_icore_open/theme/sphinx_icore_open/static/img/icons/tabler/arrow-up-right.svg
sphinx_icore_open/theme/sphinx_icore_open/static/img/icons/tabler/caret-down-filled.svg
sphinx_icore_open/theme/sphinx_icore_open/static/img/icons/tabler/caret-up-down-filled.svg
sphinx_icore_open/theme/sphinx_icore_open/static/img/icons/tabler/caret-up-filled.svg
sphinx_icore_open_theme-1.2.0.dist-info/METADATA
sphinx_icore_open_theme-1.2.0.dist-info/WHEEL
sphinx_icore_open_theme-1.2.0.dist-info/entry_points.txt
sphinx_icore_open_theme-1.2.0.dist-info/top_level.txt
sphinx_icore_open_theme-1.2.0.dist-info/RECORD
