Metadata-Version: 2.4
Name: sphinx-icore-open-theme
Version: 1.2.0
Summary: Sphinx theme for iCore Open
Requires-Python: >=3.11
Requires-Dist: Sphinx==8.2.3
